rtl/sdram_module.sv
// ========================================================
//  SDRAM MODULE with 4 banks ( No precharge or refresh)
// ========================================================

module sdram_module #(
    parameter DATA_WIDTH = 16,
    parameter ROW_BITS   = 11,
    parameter COL_BITS   = 8
)(
    // input clock
    input  logic clk,

    // SDRAM pins - all are active low
    input  logic cs_n, // chip select
    input  logic ras_n, // row address strobe
    input  logic cas_n, // column address strobe
    input  logic we_n, // write enable signal

    // address and data bus
    input  logic [ROW_BITS-1:0] sdram_addr,
    input  logic [1:0] bank_select, // bank select bits (2 bit address for 4 banks 00, 01, 10, 11)
    input  logic [DATA_WIDTH-1:0] dq_in, // write data bus
    output logic [DATA_WIDTH-1:0] dq_out // read data bus
);

    // Initializing all the inputs
    logic [ROW_BITS-1:0] row_init = 11'b0;
    logic [COL_BITS-1:0] col_init = 8'b0;
    logic [1:0] bank_select_init = 2'b0;
    logic [1:0] nop_count =  2'b0; // required as idle states to allow proper timing and sequencing of SDRAM operations

    // to integrate the data write latency and read latency , write and read completion flags
    logic write_flag = 1'b0, read_flag = 1'b0;

    // Commands
    wire cmd_activate   = ~cs_n & ~ras_n &  cas_n & we_n; // select bank and activate row
    wire cmd_read       = ~cs_n &  ras_n & ~cas_n & we_n; // select bank and column, start read burst
    wire cmd_write      = ~cs_n &  ras_n & ~cas_n & ~we_n; // select bank and column, start write burst
    wire cmd_nop        = ~cs_n & ras_n & cas_n & we_n; // no operation        
    wire write_ready    = (nop_count == 2 && cmd_nop && write_flag) ? 1'b1 :  1'b0; // data is ready to be written into memory

    // Defining each bank seperately with its own row buffer having column access ( initial flattening of array in the code itself)
    // Instead of [datawidth] mem [bank][row][col]

    // This memory mapping created an issue as the Memory is supposed to be 2^ROW_BITS and 2^COL_BITS
    // logic [DATA_WIDTH-1:0] b0 [0:ROW_BITS - 1][0:COL_BITS - 1];
    // logic [DATA_WIDTH-1:0] b1 [0:ROW_BITS - 1][0:COL_BITS - 1];
    // logic [DATA_WIDTH-1:0] b2 [0:ROW_BITS - 1][0:COL_BITS - 1];
    // logic [DATA_WIDTH-1:0] b3 [0:ROW_BITS - 1][0:COL_BITS - 1];

    logic [DATA_WIDTH-1:0] b0 [0:(1<<ROW_BITS)-1][0:(1<<COL_BITS)-1];
    logic [DATA_WIDTH-1:0] b1 [0:(1<<ROW_BITS)-1][0:(1<<COL_BITS)-1];
    logic [DATA_WIDTH-1:0] b2 [0:(1<<ROW_BITS)-1][0:(1<<COL_BITS)-1];
    logic [DATA_WIDTH-1:0] b3 [0:(1<<ROW_BITS)-1][0:(1<<COL_BITS)-1];

    // To differentiate each bank 
    localparam  BANK0 = 2'b00,
                BANK1 = 2'b01,
                BANK2 = 2'b10,
                BANK3 = 2'b11;

    // Fixing the writes with a write buffer to store data
    logic [DATA_WIDTH-1:0] write_data_buf;
    logic [ROW_BITS-1:0] write_row_buf;
    logic [COL_BITS-1:0] write_col_buf;
    logic [1:0] write_bank_buf;

    
    // Sequential Logic for NOP and R/W memory blocks
    always_ff @( posedge clk ) begin
        // chip select is active low
        if(!cs_n) begin
            if(cmd_activate) begin 
                row_init <= sdram_addr[ROW_BITS-1:0];
                bank_select_init <= bank_select;
            end
            else if (cmd_read || cmd_write) begin 
                col_init <= sdram_addr[COL_BITS-1:0];
                bank_select_init <= bank_select;
                // if read - write_flag will stay as 0, but if write - write_flag = 1
                write_flag <= cmd_write;

                if(cmd_write) begin 
                    write_data_buf <= dq_in;
                    write_row_buf <= row_init;
                    write_col_buf <= sdram_addr[COL_BITS-1:0];
                    write_bank_buf <= bank_select;
                    nop_count <= 2'b0; // Reset counter for NOPs
                end
            end
            else begin
                
            end

            // increment NOP count when write is pending
            if (write_flag && cmd_nop) begin
                if(nop_count < 2) begin
                    nop_count <= nop_count + 1;
                end
                else begin
                    
                end
            end
            else begin
                
            end
            
            if(write_ready) begin
                write_flag <= 1'b0;
                nop_count <= 2'b0;
            end
            else begin
                
            end
        end
        else begin
            
        end

        // Memory write should be sequential for selecting the banks to write data or read from the bank
        if (write_ready) begin
            case (write_bank_buf)
                BANK0:begin
                    b0[write_row_buf][write_col_buf] = write_data_buf;
                end
                BANK1:begin
                    b1[write_row_buf][write_col_buf] = write_data_buf;
                end
                BANK2:begin
                    b2[write_row_buf][write_col_buf] = write_data_buf;
                end
                BANK3:begin
                    b3[write_row_buf][write_col_buf] = write_data_buf;
                end 
                default: begin
                    
                end 
            endcase
        end
        else begin
            
        end

        // if the we_n is high, we are in the read state
        if(!cs_n && we_n && !cmd_activate) begin
           case (bank_select_init)
            BANK0:begin
                dq_out <= b0[row_init][col_init]; 
            end
            BANK1:begin
                dq_out <= b1[row_init][col_init]; 
            end
            BANK2:begin
                dq_out <= b2[row_init][col_init]; 
            end
            BANK3:begin
                dq_out <= b3[row_init][col_init]; 
            end 
            default: begin
                dq_out <= '0;
            end
           endcase 
        end
        else begin
            
        end
    end


endmodule

verify/sdram_tb.sv
`timescale 1ns/1ps

module sdram_tb;

    // Parameters
    localparam DATA_WIDTH = 16;
    localparam ROW_BITS   = 11;
    localparam COL_BITS   = 8;


    // -----------------------
    // Signals
    // -----------------------
    logic cs_n, ras_n, cas_n, we_n;
    logic [ROW_BITS-1:0] sdram_addr;
    logic [1:0] bank_select;
    logic [DATA_WIDTH-1:0] dq_in;
    logic [DATA_WIDTH-1:0] dq_out;

    // -----------------------
    // DUT
    // -----------------------
    sdram_module #(
        .DATA_WIDTH(DATA_WIDTH),
        .ROW_BITS(ROW_BITS),
        .COL_BITS(COL_BITS) 
        ) dut (
        .clk(clk),
        .cs_n(cs_n),
        .ras_n(ras_n),
        .cas_n(cas_n),
        .we_n(we_n),
        .sdram_addr(sdram_addr),
        .bank_select(bank_select),
        .dq_in(dq_in),
        .dq_out(dq_out)
    );

    // -----------------------
    // Clock
    // -----------------------
    logic clk;
    always #5 clk = ~clk;   // 100 MHz


    // -----------------------
    // SDRAM command tasks
    // -----------------------
    task cmd_nop();
        begin
            cs_n  = 0;
            ras_n = 1;
            cas_n = 1;
            we_n  = 1;
            @(posedge clk);
        end
    endtask

    task cmd_activate(input [1:0] bank, 
                      input [ROW_BITS-1:0] row);
        begin
            cs_n         = 0;
            ras_n        = 0;
            cas_n        = 1;
            we_n         = 1;
            sdram_addr   = row;
            bank_select  = bank;
            @(posedge clk);
        end
    endtask

    task cmd_write(input [1:0] bank,
                   input [COL_BITS-1:0] col,
                   input [DATA_WIDTH-1:0] data);
        begin
            cs_n         = 0;
            ras_n        = 1;
            cas_n        = 0;
            we_n         = 0;
            sdram_addr   = {{(ROW_BITS-COL_BITS){1'b0}}, col};
            bank_select  = bank;
            dq_in        = data;
            @(posedge clk);
        end
    endtask

    task cmd_read(input [1:0] bank, 
                  input [COL_BITS-1:0] col);
        begin
            cs_n         = 0;
            ras_n        = 1;
            cas_n        = 0;
            we_n         = 1;
            sdram_addr   = {{(ROW_BITS-COL_BITS){1'b0}}, col};
            bank_select  = bank;
            @(posedge clk);
        end
    endtask

    task write_data(input [1:0] bank, 
                    input [ROW_BITS-1:0] row, 
                    input [COL_BITS-1:0] col,
                    input [DATA_WIDTH-1:0] data);
        begin
            $display("[%0t] Writing: Bank=%0d, Row=%0d, Col=%0d, Data=0x%0h", $time, bank, row, col, data);
            cmd_activate(bank, row);
            //tRCD - time from ACTIVATE to ACCESS ROW/COLUMN (2 cycles)
            cmd_write(bank, col, data);
            //tWR - write recovery time (3 cycles)
            cmd_nop();
            cmd_nop();
            cmd_nop(); // write_ready activates when nop_count = 2 on the 3rd NOP
        end
    endtask

    task  read_data(input [1:0] bank,
                    input [ROW_BITS-1:0] row, 
                    input [COL_BITS-1:0] col);
        begin
            $display("[%0t] Reading: Bank=%0d, Row=%0d, Col=%0d", $time, bank, row, col);
            cmd_activate(bank, row);
            cmd_read(bank, col);
            // CL - time from read to data output ( CAS Latency) (1 cycle)
            @(posedge clk); // wait for read to finish
            @(posedge clk); // read data on dq_out
            $display("[%0t] Read Data: 0x%0h", $time, dq_out);
        end
    endtask

    // -----------------------
    // Main Test sequence
    // -----------------------
    initial begin
        $dumpfile("SDRAM.vcd");
        $dumpvars(0, dut);

        // Initialize signals
        clk          = 0;
        cs_n         = 1;
        ras_n        = 1;
        cas_n        = 1;
        we_n         = 1;
        sdram_addr   = 0;
        bank_select  = 0;
        dq_in        = 0;

        // Wait a few cycles
        repeat(5) @(posedge clk);
        $display("\n====================================================================================");
        $display("                                         SDRAM Testbench                              ");        
        $display("======================================================================================");
        $display("Memory Size: %0d rows × %0d cols × 16 bits × 4 banks", (1<<ROW_BITS), (1<<COL_BITS));
        $display("Total Memory: %0d Kb", ((1<<ROW_BITS) * (1<<COL_BITS) * 16 * 4) / 1024);
        
        // TEST 1: Bank 0
        $display("\nTEST 1: Bank 0 write");
        write_data(2'b00, 11'd5, 8'd10, 16'hA5A5);
        repeat(2) @(posedge clk);
        
        $display("\nTEST 1: Bank 0 read");
        read_data(2'b00, 11'd5, 8'd10);
        repeat(2) @(posedge clk);

        // TEST 2: Writing/Reading - multiple banks
        $display("\nTEST 2: Write to multiple banks ");
        write_data(2'b00, 11'd1, 8'd2, 16'h1111);
        write_data(2'b01, 11'd3, 8'd4, 16'h2222);
        write_data(2'b10, 11'd5, 8'd6, 16'h3333);
        write_data(2'b11, 11'd7, 8'd8, 16'h4444);
        repeat(2) @(posedge clk);

        $display("\nTEST 2: Read from multiple banks ");
        read_data(2'b00, 11'd1, 8'd2);
        read_data(2'b01, 11'd3, 8'd4);
        read_data(2'b10, 11'd5, 8'd6);
        read_data(2'b11, 11'd7, 8'd8);
        repeat(2) @(posedge clk);

        // TEST 3: Immediate Read/Write to same bank
        $display("\nTEST 3: Immediate Read and Write ");
        write_data(2'b10, 11'd100, 8'd200, 16'h5555);
        //repeat(3) @(posedge clk);
        read_data(2'b10, 11'd100, 8'd200);
        repeat(2) @(posedge clk);

        // TEST 4: Sequential Writes to the same bank
        $display("\nTEST 4: Sequential Writes to same row, different col");
        write_data(2'b11, 11'd50, 8'd7, 16'hAAAA);
        write_data(2'b11, 11'd50, 8'd8, 16'hBBBB);
        write_data(2'b11, 11'd50, 8'd9, 16'hCCCC);
        repeat(2) @(posedge clk);


        // TEST 5: Sequential Reads from same bank
        $display("\nTEST 5: Sequential Reads to Verify previous Writes to same row, different col");
        read_data(2'b11, 11'd50, 8'd7);
        read_data(2'b11, 11'd50, 8'd8);
        read_data(2'b11, 11'd50, 8'd9);
        repeat(2) @(posedge clk);

        // TEST 6: Edge Cases
        $display("\nTEST 6: Edge Cases: Max Addresses");
        write_data(2'b00, 11'd2047, 8'd255, 16'hFFFF);
        read_data(2'b00, 11'd2047, 8'd255);
        repeat(2) @(posedge clk);
        
        
        $display("\n====================================================================================");
        $display("                             SDRAM Testbench Completed                                ");        
        $display("======================================================================================");
        
        repeat(10) @(posedge clk);
        $finish;
    end

    // Monitor for debugging
    initial begin
        $monitor("Time=%0t | cs_n=%b ras_n=%b cas_n=%b we_n=%b | Bank=%0d Addr=%0d | dq_in=0x%0h dq_out=0x%0h", 
                 $time, cs_n, ras_n, cas_n, we_n, bank_select, sdram_addr, dq_in, dq_out);
    end

endmodule

SDRAM.vcd
$date
	Mon Jan 19 16:28:57 2026
$end
$version
	Icarus Verilog
$end
$timescale
	1ps
$end
$scope module sdram_tb $end
$scope module dut $end
$var wire 2 ! bank_select [1:0] $end
$var wire 1 " cas_n $end
$var wire 1 # clk $end
$var wire 1 $ cmd_activate $end
$var wire 1 % cmd_nop $end
$var wire 1 & cmd_read $end
$var wire 1 ' cmd_write $end
$var wire 1 ( cs_n $end
$var wire 16 ) dq_in [15:0] $end
$var wire 1 * ras_n $end
$var wire 11 + sdram_addr [10:0] $end
$var wire 1 , we_n $end
$var wire 1 - write_ready $end
$var reg 2 . bank_select_init [1:0] $end
$var reg 8 / col_init [7:0] $end
$var reg 16 0 dq_out [15:0] $end
$var reg 2 1 nop_count [1:0] $end
$var reg 1 2 read_flag $end
$var reg 11 3 row_init [10:0] $end
$var reg 2 4 write_bank_buf [1:0] $end
$var reg 8 5 write_col_buf [7:0] $end
$var reg 16 6 write_data_buf [15:0] $end
$var reg 1 7 write_flag $end
$var reg 11 8 write_row_buf [10:0] $end
$upscope $end
$upscope $end
$enddefinitions $end
#0
$dumpvars
bx 8
07
bx 6
bx 5
bx 4
b0 3
02
b0 1
bx 0
b0 /
b0 .
0-
1,
b0 +
1*
b0 )
1(
0'
0&
0%
0$
0#
1"
b0 !
$end
#5000
1#
#10000
0#
#15000
1#
#20000
0#
#25000
1#
#30000
0#
#35000
1#
#40000
0#
#45000
1$
b101 +
0*
0(
1#
#50000
0#
#55000
b101 3
1'
0$
b1010010110100101 )
b1010 +
0,
0"
1*
1#
#60000
0#
#65000
b0 4
b1010 5
b101 8
b1010010110100101 6
17
b1010 /
0'
0&
1%
1,
1"
1#
#70000
0#
#75000
b1 1
1#
#80000
0#
#85000
1-
b10 1
1#
#90000
0#
#95000
0-
b1010010110100101 0
b0 1
07
1#
#100000
0#
#105000
1#
#110000
0#
#115000
1$
0%
b101 +
0*
1#
#120000
0#
#125000
1&
0$
b1010 +
0"
1*
1#
#130000
0#
#135000
1#
#140000
0#
#145000
1#
#150000
0#
#155000
1#
#160000
0#
#165000
1#
#170000
0#
#175000
1$
0&
b1 +
1"
0*
1#
#180000
0#
#185000
b1 3
1'
0$
b1000100010001 )
b10 +
0,
0"
1*
1#
#190000
0#
#195000
b10 5
b1 8
b1000100010001 6
17
b10 /
0'
0&
1%
1,
1"
1#
#200000
0#
#205000
bx 0
b1 1
1#
#210000
0#
#215000
1-
b10 1
1#
#220000
0#
#225000
b1000100010001 0
b0 1
07
0-
1$
0%
b1 !
b11 +
0*
1#
#230000
0#
#235000
b1 .
b11 3
1'
0$
b10001000100010 )
b100 +
0,
0"
1*
1#
#240000
0#
#245000
b1 4
b100 5
b11 8
b10001000100010 6
17
b100 /
0'
0&
1%
1,
1"
1#
#250000
0#
#255000
bx 0
b1 1
1#
#260000
0#
#265000
1-
b10 1
1#
#270000
0#
#275000
b10001000100010 0
b0 1
07
0-
1$
0%
b10 !
b101 +
0*
1#
#280000
0#
#285000
b10 .
b101 3
1'
0$
b11001100110011 )
b110 +
0,
0"
1*
1#
#290000
0#
#295000
b10 4
b110 5
b101 8
b11001100110011 6
17
b110 /
0'
0&
1%
1,
1"
1#
#300000
0#
#305000
bx 0
b1 1
1#
#310000
0#
#315000
1-
b10 1
1#
#320000
0#
#325000
b11001100110011 0
b0 1
07
0-
1$
0%
b11 !
b111 +
0*
1#
#330000
0#
#335000
b11 .
b111 3
1'
0$
b100010001000100 )
b1000 +
0,
0"
1*
1#
#340000
0#
#345000
b11 4
b1000 5
b111 8
b100010001000100 6
17
b1000 /
0'
0&
1%
1,
1"
1#
#350000
0#
#355000
bx 0
b1 1
1#
#360000
0#
#365000
1-
b10 1
1#
#370000
0#
#375000
0-
b100010001000100 0
b0 1
07
1#
#380000
0#
#385000
1#
#390000
0#
#395000
1$
0%
b0 !
b1 +
0*
1#
#400000
0#
#405000
b0 .
b1 3
1&
0$
b10 +
0"
1*
1#
#410000
0#
#415000
bx 0
b10 /
1#
#420000
0#
#425000
b1000100010001 0
1#
#430000
0#
#435000
1$
0&
b1 !
b11 +
1"
0*
1#
#440000
0#
#445000
b1 .
b11 3
1&
0$
b100 +
0"
1*
1#
#450000
0#
#455000
bx 0
b100 /
1#
#460000
0#
#465000
b10001000100010 0
1#
#470000
0#
#475000
1$
0&
b10 !
b101 +
1"
0*
1#
#480000
0#
#485000
b10 .
b101 3
1&
0$
b110 +
0"
1*
1#
#490000
0#
#495000
bx 0
b110 /
1#
#500000
0#
#505000
b11001100110011 0
1#
#510000
0#
#515000
1$
0&
b11 !
b111 +
1"
0*
1#
#520000
0#
#525000
b11 .
b111 3
1&
0$
b1000 +
0"
1*
1#
#530000
0#
#535000
bx 0
b1000 /
1#
#540000
0#
#545000
b100010001000100 0
1#
#550000
0#
#555000
1#
#560000
0#
#565000
1#
#570000
0#
#575000
1$
0&
b10 !
b1100100 +
1"
0*
1#
#580000
0#
#585000
b10 .
b1100100 3
1'
0$
b101010101010101 )
b11001000 +
0,
0"
1*
1#
#590000
0#
#595000
b10 4
b11001000 5
b1100100 8
b101010101010101 6
17
b11001000 /
0'
0&
1%
1,
1"
1#
#600000
0#
#605000
bx 0
b1 1
1#
#610000
0#
#615000
1-
b10 1
1#
#620000
0#
#625000
b101010101010101 0
b0 1
07
0-
1$
0%
b1100100 +
0*
1#
#630000
0#
#635000
1&
0$
b11001000 +
0"
1*
1#
#640000
0#
#645000
1#
#650000
0#
#655000
1#
#660000
0#
#665000
1#
#670000
0#
#675000
1#
#680000
0#
#685000
1$
0&
b11 !
b110010 +
1"
0*
1#
#690000
0#
#695000
b11 .
b110010 3
1'
0$
b1010101010101010 )
b111 +
0,
0"
1*
1#
#700000
0#
#705000
b11 4
b111 5
b110010 8
b1010101010101010 6
17
b111 /
0'
0&
1%
1,
1"
1#
#710000
0#
#715000
bx 0
b1 1
1#
#720000
0#
#725000
1-
b10 1
1#
#730000
0#
#735000
b1010101010101010 0
b0 1
07
0-
1$
0%
b110010 +
0*
1#
#740000
0#
#745000
1'
0$
b1011101110111011 )
b1000 +
0,
0"
1*
1#
#750000
0#
#755000
b1000 5
b1011101110111011 6
17
b1000 /
0'
0&
1%
1,
1"
1#
#760000
0#
#765000
bx 0
b1 1
1#
#770000
0#
#775000
1-
b10 1
1#
#780000
0#
#785000
b1011101110111011 0
b0 1
07
0-
1$
0%
b110010 +
0*
1#
#790000
0#
#795000
1'
0$
b1100110011001100 )
b1001 +
0,
0"
1*
1#
#800000
0#
#805000
b1001 5
b1100110011001100 6
17
b1001 /
0'
0&
1%
1,
1"
1#
#810000
0#
#815000
bx 0
b1 1
1#
#820000
0#
#825000
1-
b10 1
1#
#830000
0#
#835000
0-
b1100110011001100 0
b0 1
07
1#
#840000
0#
#845000
1#
#850000
0#
#855000
1$
0%
b110010 +
0*
1#
#860000
0#
#865000
1&
0$
b111 +
0"
1*
1#
#870000
0#
#875000
b111 /
1#
#880000
0#
#885000
b1010101010101010 0
1#
#890000
0#
#895000
1$
0&
b110010 +
1"
0*
1#
#900000
0#
#905000
1&
0$
b1000 +
0"
1*
1#
#910000
0#
#915000
b1000 /
1#
#920000
0#
#925000
b1011101110111011 0
1#
#930000
0#
#935000
1$
0&
b110010 +
1"
0*
1#
#940000
0#
#945000
1&
0$
b1001 +
0"
1*
1#
#950000
0#
#955000
b1001 /
1#
#960000
0#
#965000
b1100110011001100 0
1#
#970000
0#
#975000
1#
#980000
0#
#985000
1#
#990000
0#
#995000
1$
0&
b0 !
b11111111111 +
1"
0*
1#
#1000000
0#
#1005000
b0 .
b11111111111 3
1'
0$
b1111111111111111 )
b11111111 +
0,
0"
1*
1#
#1010000
0#
#1015000
b0 4
b11111111 5
b11111111111 8
b1111111111111111 6
17
b11111111 /
0'
0&
1%
1,
1"
1#
#1020000
0#
#1025000
bx 0
b1 1
1#
#1030000
0#
#1035000
1-
b10 1
1#
#1040000
0#
#1045000
b1111111111111111 0
b0 1
07
0-
1$
0%
b11111111111 +
0*
1#
#1050000
0#
#1055000
1&
0$
b11111111 +
0"
1*
1#
